{
    "Products": [
        {
            "id": 1,
            "product_name": "UNDECYLENIC ACID",
            "image_url": "http://dummyimage.com/230x100.png/ff4444/ffffff",
            "price": 377,
            "review": null
        },
        {
            "id": 2,
            "product_name": "Metformin Hydrochloride",
            "image_url": "http://dummyimage.com/132x100.png/5fa2dd/ffffff",
            "price": 22,
            "review": null
        },
        {
            "id": 3,
            "product_name": "ibuprofen",
            "image_url": "http://dummyimage.com/206x100.png/cc0000/ffffff",
            "price": 376,
            "review": null
        },
        {
            "id": 4,
            "product_name": "Sodium fluoride",
            "image_url": "http://dummyimage.com/150x100.png/5fa2dd/ffffff",
            "price": 155,
            "review": null
        },
        {
            "id": 5,
            "product_name": "Curly Dock",
            "image_url": "http://dummyimage.com/147x100.png/dddddd/000000",
            "price": 411,
            "review": null
        },
        {
            "id": 6,
            "product_name": "Naproxen Sodium",
            "image_url": "http://dummyimage.com/165x100.png/5fa2dd/ffffff",
            "price": 354,
            "review": null
        },
        {
            "id": 7,
            "product_name": "Agnus Castus 30c, Cimicifuga 30c, Nat Mur 30c, Platina 30c, Pulsatilla 30c, Sepia 30c, Sulphur 30c, Tarentula 30c Veratrum Vir 30c",
            "image_url": "http://dummyimage.com/219x100.png/5fa2dd/ffffff",
            "price": 86,
            "review": null
        },
        {
            "id": 8,
            "product_name": "paroxetine hydrochloride hemihydrate",
            "image_url": "http://dummyimage.com/163x100.png/dddddd/000000",
            "price": 344,
            "review": null
        },
        {
            "id": 9,
            "product_name": "Meperidine Hydrochloride",
            "image_url": "http://dummyimage.com/127x100.png/dddddd/000000",
            "price": 449,
            "review": null
        },
        {
            "id": 10,
            "product_name": "Dimethicone, Octinoxate, and Oxybenzone",
            "image_url": "http://dummyimage.com/235x100.png/dddddd/000000",
            "price": 462,
            "review": null
        },
        {
            "id": 11,
            "product_name": "Oxygen",
            "image_url": "http://dummyimage.com/245x100.png/cc0000/ffffff",
            "price": 467,
            "review": null
        },
        {
            "id": 12,
            "product_name": "Acitretin",
            "image_url": "http://dummyimage.com/169x100.png/dddddd/000000",
            "price": 437,
            "review": null
        },
        {
            "id": 13,
            "product_name": "Ranitidine Hydrochloride",
            "image_url": "http://dummyimage.com/210x100.png/cc0000/ffffff",
            "price": 199,
            "review": null
        },
        {
            "id": 14,
            "product_name": "Psyllium Husk",
            "image_url": "http://dummyimage.com/233x100.png/5fa2dd/ffffff",
            "price": 292,
            "review": null
        },
        {
            "id": 15,
            "product_name": "Viscum Belladonna",
            "image_url": "http://dummyimage.com/201x100.png/ff4444/ffffff",
            "price": 60,
            "review": null
        },
        {
            "id": 16,
            "product_name": "Red (River) Birch",
            "image_url": "http://dummyimage.com/236x100.png/ff4444/ffffff",
            "price": 26,
            "review": null
        },
        {
            "id": 17,
            "product_name": "Adrenal Support",
            "image_url": "http://dummyimage.com/206x100.png/ff4444/ffffff",
            "price": 65,
            "review": null
        },
        {
            "id": 18,
            "product_name": "NEOMYCIN AND POLYMYXIN B SULFATES, BACITRACIN ZINC, AND HYDROCORTISONE ACETATE",
            "image_url": "http://dummyimage.com/208x100.png/dddddd/000000",
            "price": 399,
            "review": null
        },
        {
            "id": 19,
            "product_name": "Avobenzone, Homosalate, Octisalate, Octocrylene, and Oxybenzone",
            "image_url": "http://dummyimage.com/156x100.png/cc0000/ffffff",
            "price": 254,
            "review": null
        },
        {
            "id": 20,
            "product_name": "Aluminum Zirconium Tetrachlorohydrex GLY",
            "image_url": "http://dummyimage.com/195x100.png/cc0000/ffffff",
            "price": 148,
            "review": null
        },
        {
            "id": 21,
            "product_name": "minocycline hydrochloride",
            "image_url": "http://dummyimage.com/108x100.png/dddddd/000000",
            "price": 160,
            "review": null
        },
        {
            "id": 22,
            "product_name": "Alcohol",
            "image_url": "http://dummyimage.com/216x100.png/5fa2dd/ffffff",
            "price": 102,
            "review": null
        },
        {
            "id": 23,
            "product_name": "estradiol",
            "image_url": "http://dummyimage.com/121x100.png/dddddd/000000",
            "price": 24,
            "review": null
        },
        {
            "id": 24,
            "product_name": "ASPERGILLUS NIGER VAR. NIGER - CANDIDA ALBICANS - CENTELLA ASIATICA - MALIC ACID - MERCURIC CHLORIDE - RHIZOPUS STOLONIFER - SODIUM DIETHYL OXALACETATE - SULFUR - TABEBUIA IMPETIGINOSA BARK -",
            "image_url": "http://dummyimage.com/237x100.png/5fa2dd/ffffff",
            "price": 470,
            "review": null
        },
        {
            "id": 25,
            "product_name": "Meclizine HCl",
            "image_url": "http://dummyimage.com/201x100.png/5fa2dd/ffffff",
            "price": 29,
            "review": null
        },
        {
            "id": 26,
            "product_name": "Labetalol HCl",
            "image_url": "http://dummyimage.com/233x100.png/dddddd/000000",
            "price": 427,
            "review": null
        },
        {
            "id": 27,
            "product_name": "Diphenhydramine Hydrochloride",
            "image_url": "http://dummyimage.com/136x100.png/dddddd/000000",
            "price": 57,
            "review": null
        },
        {
            "id": 28,
            "product_name": "Calendula Officinalis Flowering Top",
            "image_url": "http://dummyimage.com/188x100.png/ff4444/ffffff",
            "price": 188,
            "review": null
        },
        {
            "id": 29,
            "product_name": "Clam",
            "image_url": "http://dummyimage.com/162x100.png/dddddd/000000",
            "price": 31,
            "review": null
        },
        {
            "id": 30,
            "product_name": "Amlodipine Besylate and Benazepril Hydrochloride",
            "image_url": "http://dummyimage.com/244x100.png/ff4444/ffffff",
            "price": 489,
            "review": null
        },
        {
            "id": 31,
            "product_name": "Lisinopril and Hydrochlorothiazide",
            "image_url": "http://dummyimage.com/197x100.png/5fa2dd/ffffff",
            "price": 278,
            "review": null
        },
        {
            "id": 32,
            "product_name": "Triclosan",
            "image_url": "http://dummyimage.com/168x100.png/cc0000/ffffff",
            "price": 455,
            "review": null
        },
        {
            "id": 33,
            "product_name": "Salicylic Acid",
            "image_url": "http://dummyimage.com/146x100.png/dddddd/000000",
            "price": 241,
            "review": null
        },
        {
            "id": 34,
            "product_name": "Aluminum Zirconium Tetrachlorohydrex GLY",
            "image_url": "http://dummyimage.com/137x100.png/cc0000/ffffff",
            "price": 305,
            "review": null
        },
        {
            "id": 35,
            "product_name": "Naproxen",
            "image_url": "http://dummyimage.com/117x100.png/ff4444/ffffff",
            "price": 220,
            "review": null
        },
        {
            "id": 36,
            "product_name": "hydroxyzine pamoate",
            "image_url": "http://dummyimage.com/232x100.png/5fa2dd/ffffff",
            "price": 113,
            "review": null
        },
        {
            "id": 37,
            "product_name": "Naproxen",
            "image_url": "http://dummyimage.com/227x100.png/dddddd/000000",
            "price": 162,
            "review": null
        },
        {
            "id": 38,
            "product_name": "Venlafaxine Hydrochloride",
            "image_url": "http://dummyimage.com/206x100.png/dddddd/000000",
            "price": 290,
            "review": null
        },
        {
            "id": 39,
            "product_name": "MORPHINE SULFATE and NALTREXONE HYDROCHLORIDE",
            "image_url": "http://dummyimage.com/225x100.png/cc0000/ffffff",
            "price": 72,
            "review": null
        },
        {
            "id": 40,
            "product_name": "Acetaminophen, Diphenhydramine HCl",
            "image_url": "http://dummyimage.com/164x100.png/dddddd/000000",
            "price": 115,
            "review": null
        },
        {
            "id": 41,
            "product_name": "Benzalkonium Chloride",
            "image_url": "http://dummyimage.com/223x100.png/cc0000/ffffff",
            "price": 151,
            "review": null
        },
        {
            "id": 42,
            "product_name": "Hydrocortisone",
            "image_url": "http://dummyimage.com/133x100.png/dddddd/000000",
            "price": 419,
            "review": null
        },
        {
            "id": 43,
            "product_name": "Ioflupane I-123 and iodine",
            "image_url": "http://dummyimage.com/120x100.png/5fa2dd/ffffff",
            "price": 184,
            "review": null
        },
        {
            "id": 44,
            "product_name": "Adenosine triphosphate, Coenzyme A, Coenzyme Q10, Pineal Gland Suis, Sarcolacticum acidum, Melatonin, Pyrrole, Tryptophan, Arsenicum album, Avena sativa,",
            "image_url": "http://dummyimage.com/130x100.png/5fa2dd/ffffff",
            "price": 303,
            "review": null
        },
        {
            "id": 45,
            "product_name": "Hydroxyzine Hydrochloride",
            "image_url": "http://dummyimage.com/194x100.png/dddddd/000000",
            "price": 248,
            "review": null
        },
        {
            "id": 46,
            "product_name": "Ethyl Alcohol",
            "image_url": "http://dummyimage.com/151x100.png/dddddd/000000",
            "price": 390,
            "review": null
        },
        {
            "id": 47,
            "product_name": "Clemastine Fumarate",
            "image_url": "http://dummyimage.com/132x100.png/5fa2dd/ffffff",
            "price": 487,
            "review": null
        },
        {
            "id": 48,
            "product_name": "Benzocain",
            "image_url": "http://dummyimage.com/207x100.png/cc0000/ffffff",
            "price": 368,
            "review": null
        },
        {
            "id": 49,
            "product_name": "Sodium Monofluorophosphate",
            "image_url": "http://dummyimage.com/200x100.png/ff4444/ffffff",
            "price": 75,
            "review": null
        },
        {
            "id": 50,
            "product_name": "epinephrine",
            "image_url": "http://dummyimage.com/220x100.png/ff4444/ffffff",
            "price": 161,
            "review": null
        },
        {
            "id": 51,
            "product_name": "Simvastatin",
            "image_url": "http://dummyimage.com/225x100.png/cc0000/ffffff",
            "price": 65,
            "review": null
        },
        {
            "id": 52,
            "product_name": "EUCALYPTOL, MENTHOL, METYL SALICYLATE, THYMOL",
            "image_url": "http://dummyimage.com/137x100.png/dddddd/000000",
            "price": 235,
            "review": null
        },
        {
            "id": 53,
            "product_name": "Omeprazole",
            "image_url": "http://dummyimage.com/225x100.png/dddddd/000000",
            "price": 428,
            "review": null
        },
        {
            "id": 54,
            "product_name": "Treatment Set TS344592",
            "image_url": "http://dummyimage.com/198x100.png/dddddd/000000",
            "price": 50,
            "review": null
        },
        {
            "id": 55,
            "product_name": "House Dust",
            "image_url": "http://dummyimage.com/188x100.png/ff4444/ffffff",
            "price": 69,
            "review": null
        },
        {
            "id": 56,
            "product_name": "methylphenidate hydrochloride",
            "image_url": "http://dummyimage.com/189x100.png/ff4444/ffffff",
            "price": 354,
            "review": null
        },
        {
            "id": 57,
            "product_name": "Tretinoin",
            "image_url": "http://dummyimage.com/161x100.png/5fa2dd/ffffff",
            "price": 85,
            "review": null
        },
        {
            "id": 58,
            "product_name": "BENZALKONIUM CHLORIDE",
            "image_url": "http://dummyimage.com/104x100.png/5fa2dd/ffffff",
            "price": 309,
            "review": null
        },
        {
            "id": 59,
            "product_name": "medroxyprogesterone acetate",
            "image_url": "http://dummyimage.com/162x100.png/5fa2dd/ffffff",
            "price": 182,
            "review": null
        },
        {
            "id": 60,
            "product_name": "Flurazepam Hydrochloride",
            "image_url": "http://dummyimage.com/150x100.png/ff4444/ffffff",
            "price": 125,
            "review": null
        },
        {
            "id": 61,
            "product_name": "Pseudoephedrine Hydrochloride",
            "image_url": "http://dummyimage.com/230x100.png/dddddd/000000",
            "price": 226,
            "review": null
        },
        {
            "id": 62,
            "product_name": "Candesartan Cilexetil and Hydrochlorothiazide",
            "image_url": "http://dummyimage.com/233x100.png/dddddd/000000",
            "price": 338,
            "review": null
        },
        {
            "id": 63,
            "product_name": "Sulindac",
            "image_url": "http://dummyimage.com/215x100.png/cc0000/ffffff",
            "price": 290,
            "review": null
        },
        {
            "id": 64,
            "product_name": "Glyburide",
            "image_url": "http://dummyimage.com/119x100.png/5fa2dd/ffffff",
            "price": 72,
            "review": null
        },
        {
            "id": 65,
            "product_name": "Lidocaine Hydrochloride",
            "image_url": "http://dummyimage.com/113x100.png/5fa2dd/ffffff",
            "price": 270,
            "review": null
        },
        {
            "id": 66,
            "product_name": "Tamsulosin Hydrochloride",
            "image_url": "http://dummyimage.com/166x100.png/cc0000/ffffff",
            "price": 227,
            "review": null
        },
        {
            "id": 67,
            "product_name": "Loperamide Hydrochloride",
            "image_url": "http://dummyimage.com/202x100.png/5fa2dd/ffffff",
            "price": 259,
            "review": null
        },
        {
            "id": 68,
            "product_name": "Agrostis alba",
            "image_url": "http://dummyimage.com/195x100.png/ff4444/ffffff",
            "price": 260,
            "review": null
        },
        {
            "id": 69,
            "product_name": "Ferrous Fumarate and Polysaccharide Iron",
            "image_url": "http://dummyimage.com/217x100.png/dddddd/000000",
            "price": 251,
            "review": null
        },
        {
            "id": 70,
            "product_name": "clobetasol propionate",
            "image_url": "http://dummyimage.com/242x100.png/dddddd/000000",
            "price": 263,
            "review": null
        },
        {
            "id": 71,
            "product_name": "Ibuprofen",
            "image_url": "http://dummyimage.com/219x100.png/cc0000/ffffff",
            "price": 468,
            "review": null
        },
        {
            "id": 72,
            "product_name": "Horse Fly",
            "image_url": "http://dummyimage.com/134x100.png/ff4444/ffffff",
            "price": 487,
            "review": null
        },
        {
            "id": 73,
            "product_name": "Titanium Dioxide, Zinc Oxide",
            "image_url": "http://dummyimage.com/119x100.png/ff4444/ffffff",
            "price": 492,
            "review": null
        },
        {
            "id": 74,
            "product_name": "propranolol hydrochloride",
            "image_url": "http://dummyimage.com/191x100.png/5fa2dd/ffffff",
            "price": 326,
            "review": null
        },
        {
            "id": 75,
            "product_name": "Norethindrone",
            "image_url": "http://dummyimage.com/132x100.png/5fa2dd/ffffff",
            "price": 206,
            "review": null
        },
        {
            "id": 76,
            "product_name": "Benzalkonium Chloride",
            "image_url": "http://dummyimage.com/211x100.png/5fa2dd/ffffff",
            "price": 341,
            "review": null
        },
        {
            "id": 77,
            "product_name": "moexipril hydrochloride",
            "image_url": "http://dummyimage.com/121x100.png/5fa2dd/ffffff",
            "price": 412,
            "review": null
        },
        {
            "id": 78,
            "product_name": "Aconitum napellus, Apis mellifica, Chamomilla, Hypericum perforatum, Ledum palustre, Pulsatilla, Silicea, Thuja occidentalis",
            "image_url": "http://dummyimage.com/181x100.png/5fa2dd/ffffff",
            "price": 231,
            "review": null
        },
        {
            "id": 79,
            "product_name": "Diphenhydramine HCl, Zinc acetate",
            "image_url": "http://dummyimage.com/148x100.png/ff4444/ffffff",
            "price": 357,
            "review": null
        },
        {
            "id": 80,
            "product_name": "Indomethacin",
            "image_url": "http://dummyimage.com/181x100.png/5fa2dd/ffffff",
            "price": 421,
            "review": null
        },
        {
            "id": 81,
            "product_name": "FLUORIDE TREATMENT",
            "image_url": "http://dummyimage.com/119x100.png/dddddd/000000",
            "price": 108,
            "review": null
        },
        {
            "id": 82,
            "product_name": "PRAVASTATIN SODIUM",
            "image_url": "http://dummyimage.com/161x100.png/cc0000/ffffff",
            "price": 326,
            "review": null
        },
        {
            "id": 83,
            "product_name": "CAMPHOR (SYNTHETIC)",
            "image_url": "http://dummyimage.com/181x100.png/ff4444/ffffff",
            "price": 456,
            "review": null
        },
        {
            "id": 84,
            "product_name": "nadolol and bendroflumethiazide",
            "image_url": "http://dummyimage.com/247x100.png/5fa2dd/ffffff",
            "price": 261,
            "review": null
        },
        {
            "id": 85,
            "product_name": "Nicotine polacrilex",
            "image_url": "http://dummyimage.com/120x100.png/cc0000/ffffff",
            "price": 83,
            "review": null
        },
        {
            "id": 86,
            "product_name": "OCTINOXATE and TITANIUM DIOXIDE",
            "image_url": "http://dummyimage.com/215x100.png/ff4444/ffffff",
            "price": 373,
            "review": null
        },
        {
            "id": 87,
            "product_name": "Avobenzone Octisalate Octocrylene",
            "image_url": "http://dummyimage.com/138x100.png/cc0000/ffffff",
            "price": 226,
            "review": null
        },
        {
            "id": 88,
            "product_name": "Midazolam hydrochloride",
            "image_url": "http://dummyimage.com/205x100.png/5fa2dd/ffffff",
            "price": 154,
            "review": null
        },
        {
            "id": 89,
            "product_name": "Hydrocodone Bitartrate and Acetaminophen",
            "image_url": "http://dummyimage.com/183x100.png/cc0000/ffffff",
            "price": 493,
            "review": null
        },
        {
            "id": 90,
            "product_name": "Oxycodone hydrochloride and Acetaminophen",
            "image_url": "http://dummyimage.com/174x100.png/ff4444/ffffff",
            "price": 177,
            "review": null
        },
        {
            "id": 91,
            "product_name": "ISOPROPYL ALCOHOL",
            "image_url": "http://dummyimage.com/171x100.png/5fa2dd/ffffff",
            "price": 485,
            "review": null
        },
        {
            "id": 92,
            "product_name": "Avobenzone,Octocrylene,Oxybenzone,Homosalate,Octisalate",
            "image_url": "http://dummyimage.com/229x100.png/5fa2dd/ffffff",
            "price": 232,
            "review": null
        },
        {
            "id": 93,
            "product_name": "OXYGEN",
            "image_url": "http://dummyimage.com/236x100.png/dddddd/000000",
            "price": 497,
            "review": null
        },
        {
            "id": 94,
            "product_name": "Menthol",
            "image_url": "http://dummyimage.com/193x100.png/ff4444/ffffff",
            "price": 321,
            "review": null
        },
        {
            "id": 95,
            "product_name": "Glipizide",
            "image_url": "http://dummyimage.com/146x100.png/ff4444/ffffff",
            "price": 475,
            "review": null
        },
        {
            "id": 96,
            "product_name": "Irbesartan and Hydrochlorothiazide",
            "image_url": "http://dummyimage.com/234x100.png/cc0000/ffffff",
            "price": 262,
            "review": null
        },
        {
            "id": 97,
            "product_name": "Glandula thyreoidea 8",
            "image_url": "http://dummyimage.com/244x100.png/ff4444/ffffff",
            "price": 463,
            "review": null
        },
        {
            "id": 98,
            "product_name": "rizatriptan benzoate",
            "image_url": "http://dummyimage.com/138x100.png/5fa2dd/ffffff",
            "price": 221,
            "review": null
        },
        {
            "id": 99,
            "product_name": "Petrolatum",
            "image_url": "http://dummyimage.com/194x100.png/5fa2dd/ffffff",
            "price": 493,
            "review": null
        },
        {
            "id": 100,
            "product_name": "levonorgestrel/ethinyl estradiol and ethinyl estradiol",
            "image_url": "http://dummyimage.com/191x100.png/ff4444/ffffff",
            "price": 258,
            "review": null
        }
    ]
}